veri/assign3/Q1_nand/q1_circuit.v
// Name    : Jayant
// Roll No : <Your Roll No>
// Q1 - F = (A+B)C using NAND gates only

module nand_2 (
    input a,
    input b,
    output y
);
    assign y = ~(a & b);
endmodule

module q1_circuit (
    input a,
    input b,
    input c,
    output f
);
    wire g1, g2, g3, g4;

    // NAND as NOT: inputs tied together
    nand_2 u1 (.a(a), .b(a), .y(g1));   // g1 = A'
    nand_2 u2 (.a(b), .b(b), .y(g2));   // g2 = B'

    // OR from NAND: NAND(A', B') = A + B
    nand_2 u3 (.a(g1), .b(g2), .y(g3)); // g3 = A + B

    // AND from NAND: NAND then invert
    nand_2 u4 (.a(g3), .b(c), .y(g4));  // g4 = ((A+B)C)'
    nand_2 u5 (.a(g4), .b(g4), .y(f));  // f  = (A+B)C
endmodule

veri/assign3/Q1_nand/tb_q1.v
// Name    : Jayant
// Roll No : <Your Roll No>
// Q1 - Testbench for F = (A+B)C

module tb_q1_circuit;

    reg a, b, c;
    wire f;

    q1_circuit uut (.a(a), .b(b), .c(c), .f(f));

    initial begin
        $dumpfile("q1_waveform.vcd");
        $dumpvars(0, tb_q1_circuit);
    end

    initial begin
        $monitor("Time=%0t | A=%b B=%b C=%b | F=%b", $time, a, b, c, f);
    end

    // apply all 8 input combinations
    initial begin
        a = 0; b = 0; c = 0; #5;
        a = 0; b = 0; c = 1; #5;
        a = 0; b = 1; c = 0; #5;
        a = 0; b = 1; c = 1; #5;
        a = 1; b = 0; c = 0; #5;
        a = 1; b = 0; c = 1; #5;
        a = 1; b = 1; c = 0; #5;
        a = 1; b = 1; c = 1; #5;
        $finish;
    end

endmodule

veri/assign3/Q1_nand/q1_waveform.vcd
$date
	Wed Sep 16 21:53:11 2026
$end
$version
	Icarus Verilog
$end
$timescale
	1s
$end
$scope module tb_q1_circuit $end
$var wire 1 ! f $end
$var reg 1 " a $end
$var reg 1 # b $end
$var reg 1 $ c $end
$scope module uut $end
$var wire 1 " a $end
$var wire 1 # b $end
$var wire 1 $ c $end
$var wire 1 % g4 $end
$var wire 1 & g3 $end
$var wire 1 ' g2 $end
$var wire 1 ( g1 $end
$var wire 1 ! f $end
$scope module u1 $end
$var wire 1 " a $end
$var wire 1 " b $end
$var wire 1 ( y $end
$upscope $end
$scope module u2 $end
$var wire 1 # a $end
$var wire 1 # b $end
$var wire 1 ' y $end
$upscope $end
$scope module u3 $end
$var wire 1 ( a $end
$var wire 1 ' b $end
$var wire 1 & y $end
$upscope $end
$scope module u4 $end
$var wire 1 & a $end
$var wire 1 $ b $end
$var wire 1 % y $end
$upscope $end
$scope module u5 $end
$var wire 1 % a $end
$var wire 1 % b $end
$var wire 1 ! y $end
$upscope $end
$upscope $end
$upscope $end
$enddefinitions $end
$comment Show the parameter values. $end
$dumpall
$end
#0
$dumpvars
1(
1'
0&
1%
0$
0#
0"
0!
$end
#5
1$
#10
1&
0'
0$
1#
#15
1!
0%
1$
#20
0!
1%
1'
0(
0$
0#
1"
#25
1!
0%
1$
#30
0!
1%
0'
0$
1#
#35
1!
0%
1$
