veri/assign4/Q3_gray2bin/q3_gray2bin.v
// Name    : Jayant
// Roll No : <Your Roll No>
// Q3 - 4-bit Gray to Binary Code Converter (CSAE Assignment 4)
//
// Inputs : a, b, c, d  (4-bit Gray code, a = MSB)
// Outputs: w, x, y, z (4-bit Binary, w = MSB)
//
// Expressions (running XOR from the MSB):
//   w (B3) = a
//   x (B2) = a XOR b
//   y (B1) = a XOR b XOR c
//   z (B0) = a XOR b XOR c XOR d
//
// XOR = a.b' + a'.b ; XNOR = a.b + a'.b'

module question3 (
    input a, b, c, d,
    output w, x, y, z
);

    // Continuous assignments
    assign w = a;

    // x = A XOR B
    assign x = (a & ~b) | (~a & b);

    // y = A XOR B XOR C
    assign y = (a & ~b & ~c) | (~a & b & ~c) | (a & b & c) | (~a & ~b & c);

    // z = A XOR B XOR C XOR D
    assign z = (a & ~b & ~c & ~d) | (~a & b & ~c & ~d) |
               (~a & ~b & c & ~d) | (a & b & c & ~d) |
               (a & ~b & c & d) | (~a & b & c & d) |
               (~a & ~b & ~c & d) | (a & b & ~c & d);

endmodule

veri/assign4/Q3_gray2bin/q3_gray2bin_tb.v
// Name    : Jayant
// Roll No : <Your Roll No>
// Q3 - Testbench for 4-bit Gray to Binary Code Converter

module tb_question3;

    // Inputs & Outputs
    reg p, q, r, s;
    wire w, x, y, z;

    // Instantiate design test code
    question3 uut (
        .a(p),
        .b(q),
        .c(r),
        .d(s),
        .w(w),
        .x(x),
        .y(y),
        .z(z)
    );

    // VCD Dump setup
    initial begin
        $dumpfile("dump.vcd");
        $dumpvars(1);
    end

    // Monitor output to console
    initial begin
        $monitor("Time=%0t | Inputs: p=%b q=%b r=%b s=%b | Outputs: w=%b x=%b y=%b z=%b",
                 $time, p, q, r, s, w, x, y, z);
    end

    // Stimulus generation (all 16 Gray code combinations)
    initial begin
        p = 0; q = 0; r = 0; s = 0; #5;
        p = 0; q = 0; r = 0; s = 1; #5;
        p = 0; q = 0; r = 1; s = 1; #5;
        p = 0; q = 0; r = 1; s = 0; #5;
        p = 0; q = 1; r = 1; s = 0; #5;
        p = 0; q = 1; r = 1; s = 1; #5;
        p = 0; q = 1; r = 0; s = 1; #5;
        p = 0; q = 1; r = 0; s = 0; #5;
        p = 1; q = 1; r = 0; s = 0; #5;
        p = 1; q = 1; r = 0; s = 1; #5;
        p = 1; q = 1; r = 1; s = 1; #5;
        p = 1; q = 1; r = 1; s = 0; #5;
        p = 1; q = 0; r = 1; s = 0; #5;
        p = 1; q = 0; r = 1; s = 1; #5;
        p = 1; q = 0; r = 0; s = 1; #5;
        p = 1; q = 0; r = 0; s = 0; #5;
        $finish;
    end

endmodule

veri/assign4/Q3_gray2bin/dump.vcd
$date
	Tue Sep 22 14:45:34 2026
$end
$version
	Icarus Verilog
$end
$timescale
	1s
$end
$scope module tb_question3 $end
$var wire 1 ! z $end
$var wire 1 " y $end
$var wire 1 # x $end
$var wire 1 $ w $end
$var reg 1 % p $end
$var reg 1 & q $end
$var reg 1 ' r $end
$var reg 1 ( s $end
$upscope $end
$enddefinitions $end
$comment Show the parameter values. $end
$dumpall
$end
#0
$dumpvars
0(
0'
0&
0%
0$
0#
0"
0!
$end
#5
1!
1(
#10
0!
1"
1'
#15
1!
0(
#20
0!
0"
1#
1&
#25
1!
1(
#30
1"
0!
0'
#35
1!
0(
#40
0!
0"
0#
1$
1%
#45
1!
1(
#50
0!
1"
1'
#55
1!
0(
#60
0!
0"
1#
0&
#65
1!
1(
#70
0!
1"
0'
#75
1!
0(
