veri/assign3/Q2_boolean/q2_circuit.v
// Name    : Jayant
// Roll No : <Your Roll No>
// Q2 - F = AB + A'B + AC using basic gates

module not_gate (
    input a,
    output y
);
    assign y = ~a;
endmodule

module and_g2 (
    input a,
    input b,
    output y
);
    assign y = a & b;
endmodule

module or_g2 (
    input a,
    input b,
    output y
);
    assign y = a | b;
endmodule

module q2_circuit (
    input a,
    input b,
    input c,
    output f
);
    wire an, t1, t2, t3, t4;

    not_gate u1 (.a(a), .y(an));            // A'
    and_g2  u2 (.a(a), .b(b), .y(t1));      // AB
    and_g2  u3 (.a(an), .b(b), .y(t2));     // A'B
    and_g2  u4 (.a(a), .b(c), .y(t3));      // AC
    or_g2   u5 (.a(t1), .b(t2), .y(t4));    // AB + A'B
    or_g2   u6 (.a(t4), .b(t3), .y(f));     // F = AB + A'B + AC
endmodule

veri/assign3/Q2_boolean/tb_q2.v
// Name    : Jayant
// Roll No : <Your Roll No>
// Q2 - Testbench for F = AB + A'B + AC

module tb_q2_circuit;

    reg a, b, c;
    wire f;

    q2_circuit uut (.a(a), .b(b), .c(c), .f(f));

    initial begin
        $dumpfile("q2_waveform.vcd");
        $dumpvars(0, tb_q2_circuit);
    end

    initial begin
        $monitor("Time=%0t | A=%b B=%b C=%b | F=%b", $time, a, b, c, f);
    end

    // apply all 8 input combinations
    initial begin
        a = 0; b = 0; c = 0; #5;
        a = 0; b = 0; c = 1; #5;
        a = 0; b = 1; c = 0; #5;
        a = 0; b = 1; c = 1; #5;
        a = 1; b = 0; c = 0; #5;
        a = 1; b = 0; c = 1; #5;
        a = 1; b = 1; c = 0; #5;
        a = 1; b = 1; c = 1; #5;
        $finish;
    end

endmodule

veri/assign3/Q2_boolean/q2_waveform.vcd
$date
	Wed Sep 16 21:52:21 2026
$end
$version
	Icarus Verilog
$end
$timescale
	1s
$end
$scope module tb_q2_circuit $end
$var wire 1 ! f $end
$var reg 1 " a $end
$var reg 1 # b $end
$var reg 1 $ c $end
$scope module uut $end
$var wire 1 " a $end
$var wire 1 # b $end
$var wire 1 $ c $end
$var wire 1 % t4 $end
$var wire 1 & t3 $end
$var wire 1 ' t2 $end
$var wire 1 ( t1 $end
$var wire 1 ! f $end
$var wire 1 ) an $end
$scope module u1 $end
$var wire 1 " a $end
$var wire 1 ) y $end
$upscope $end
$scope module u2 $end
$var wire 1 " a $end
$var wire 1 # b $end
$var wire 1 ( y $end
$upscope $end
$scope module u3 $end
$var wire 1 ) a $end
$var wire 1 # b $end
$var wire 1 ' y $end
$upscope $end
$scope module u4 $end
$var wire 1 " a $end
$var wire 1 $ b $end
$var wire 1 & y $end
$upscope $end
$scope module u5 $end
$var wire 1 ( a $end
$var wire 1 ' b $end
$var wire 1 % y $end
$upscope $end
$scope module u6 $end
$var wire 1 % a $end
$var wire 1 & b $end
$var wire 1 ! y $end
$upscope $end
$upscope $end
$upscope $end
$enddefinitions $end
$comment Show the parameter values. $end
$dumpall
$end
#0
$dumpvars
1)
0(
0'
0&
0%
0$
0#
0"
0!
$end
#5
1$
#10
1!
1%
1'
0$
1#
#15
1$
#20
0!
0%
0'
0)
0$
0#
1"
#25
1!
1&
1$
#30
1%
0&
1(
0$
1#
#35
1&
1$
