veri/assign4/Q5_b2gray/q5_b2gray.v
// Name    : Jayant
// Roll No : <Your Roll No>
// Q5 - 3-bit Binary to Gray Code Converter (CSAE Assignment 4)
//
// Inputs : a, b, c  (3-bit binary, a = MSB)
// Outputs: w, x, y (3-bit Gray, w = MSB)
//
// Expressions (Binary-to-Gray rule):
//   w (G2) = a
//   x (G1) = a XOR b
//   y (G0) = b XOR c
//
// XOR = a.b' + a'.b

module question5 (
    input a, b, c,
    output w, x, y
);

    // Continuous assignments
    assign w = a;
    assign x = (a & ~b) | (~a & b);
    assign y = (b & ~c) | (~b & c);

endmodule

veri/assign4/Q5_b2gray/q5_b2gray_tb.v
// Name    : Jayant
// Roll No : <Your Roll No>
// Q5 - Testbench for 3-bit Binary to Gray Code Converter

module tb_question5;

    // Inputs & Outputs
    reg p, q, r;
    wire w, x, y;

    // Instantiate design test code
    question5 uut (
        .a(p),
        .b(q),
        .c(r),
        .w(w),
        .x(x),
        .y(y)
    );

    // VCD Dump setup
    initial begin
        $dumpfile("dump.vcd");
        $dumpvars(1);
    end

    // Monitor output to console
    initial begin
        $monitor("Time=%0t | Inputs: p=%b q=%b r=%b | Outputs: w=%b x=%b y=%b",
                 $time, p, q, r, w, x, y);
    end

    // Stimulus generation (all 8 binary input combinations)
    initial begin
        p = 0; q = 0; r = 0; #5;
        p = 0; q = 0; r = 1; #5;
        p = 0; q = 1; r = 0; #5;
        p = 0; q = 1; r = 1; #5;
        p = 1; q = 0; r = 0; #5;
        p = 1; q = 0; r = 1; #5;
        p = 1; q = 1; r = 0; #5;
        p = 1; q = 1; r = 1; #5;
        $finish;
    end

endmodule

veri/assign4/Q5_b2gray/dump.vcd
$date
	Tue Sep 22 14:45:34 2026
$end
$version
	Icarus Verilog
$end
$timescale
	1s
$end
$scope module tb_question5 $end
$var wire 1 ! y $end
$var wire 1 " x $end
$var wire 1 # w $end
$var reg 1 $ p $end
$var reg 1 % q $end
$var reg 1 & r $end
$upscope $end
$enddefinitions $end
$comment Show the parameter values. $end
$dumpall
$end
#0
$dumpvars
0&
0%
0$
0#
0"
0!
$end
#5
1!
1&
#10
1!
1"
0&
1%
#15
0!
1&
#20
1"
0&
0%
1#
1$
#25
1!
1&
#30
0"
1!
0&
1%
#35
0!
1&
