veri/assign4/Q1_b2ex3/q1_b2ex3.v
// Name    : Jayant
// Roll No : <Your Roll No>
// Q1 - 3-bit Binary to Excess-3 Code Converter (CSAE Assignment 4)
//
// Inputs : a, b, c  (3-bit binary, a = MSB)
// Outputs: d, e, f, g (4-bit Excess-3, d = MSB)
//
// Expressions (from K-map):
//   d (E3) = a.b + a.c        = a(b + c)
//   e (E2) = a'.b + a'.c + a.b'.c'
//   f (E1) = b.c + b'.c'      (B1 XNOR B0)
//   g (E0) = c'

module question1 (
    input a, b, c,
    output d, e, f, g
);

    // Continuous assignments
    assign d = (a & b) | (a & c);
    assign g = ~c;
    assign e = (~a & b) | (~a & c) | (a & ~b & ~c);
    assign f = (b & c) | (~b & ~c);

endmodule

veri/assign4/Q1_b2ex3/q1_b2ex3_tb.v
// Name    : Jayant
// Roll No : <Your Roll No>
// Q1 - Testbench for 3-bit Binary to Excess-3 Code Converter

module tb_question1;

    // Inputs & Outputs
    reg p, q, r;
    wire w, x, y, z;

    // Instantiate design test code
    question1 uut (
        .a(p),
        .b(q),
        .c(r),
        .d(w),
        .e(x),
        .f(y),
        .g(z)
    );

    // VCD Dump setup
    initial begin
        $dumpfile("dump.vcd");
        $dumpvars(1);
    end

    // Monitor output to console
    initial begin
        $monitor("Time=%0t | Inputs: p=%b q=%b r=%b | Outputs: w=%b x=%b y=%b z=%b",
                 $time, p, q, r, w, x, y, z);
    end

    // Stimulus generation
    initial begin
        p = 0; q = 0; r = 0; #5;
        p = 0; q = 0; r = 1; #5;
        p = 0; q = 1; r = 0; #5;
        p = 0; q = 1; r = 1; #5;
        p = 1; q = 0; r = 0; #5;
        p = 1; q = 0; r = 1; #5;
        p = 1; q = 1; r = 0; #5;
        p = 1; q = 1; r = 1; #5;
        $finish;
    end

endmodule

veri/assign4/Q1_b2ex3/dump.vcd
$date
	Tue Sep 22 14:45:34 2026
$end
$version
	Icarus Verilog
$end
$timescale
	1s
$end
$scope module tb_question1 $end
$var wire 1 ! z $end
$var wire 1 " y $end
$var wire 1 # x $end
$var wire 1 $ w $end
$var reg 1 % p $end
$var reg 1 & q $end
$var reg 1 ' r $end
$upscope $end
$enddefinitions $end
$comment Show the parameter values. $end
$dumpall
$end
#0
$dumpvars
0'
0&
0%
0$
0#
1"
1!
$end
#5
1#
0"
0!
1'
#10
1!
0'
1&
#15
1"
0!
1'
#20
1!
0'
0&
1%
#25
0#
0"
1$
0!
1'
#30
1!
0'
1&
#35
1"
0!
1'
