veri/assign4/Q4_bcd2ex3/q4_bcd2ex3.v
// Name    : Jayant
// Roll No : <Your Roll No>
// Q4 - BCD to Excess-3 Code Converter (CSAE Assignment 4)
//
// Inputs : a, b, c, d  (4-bit BCD, a = MSB, valid codes 0000-1001)
// Outputs: w, x, y, z (4-bit Excess-3, w = MSB)
//
// Expressions (K-map minimisation, don't cares = 1010-1111):
//   w (W) = a + b.c + b.d        = a + b(c + d)
//   x (X) = b'.c + b'.d + b.c'.d'
//   y (Y) = c.d + c'.d'          (C XNOR D)
//   z (Z) = d'

module question4 (
    input a, b, c, d,
    output w, x, y, z
);

    // Continuous assignments
    assign w = a | (b & c) | (b & d);
    assign x = (~b & c) | (~b & d) | (b & ~c & ~d);
    assign y = (c & d) | (~c & ~d);
    assign z = ~d;

endmodule

veri/assign4/Q4_bcd2ex3/q4_bcd2ex3_tb.v
// Name    : Jayant
// Roll No : <Your Roll No>
// Q4 - Testbench for BCD to Excess-3 Code Converter

module tb_question4;

    // Inputs & Outputs
    reg p, q, r, s;
    wire w, x, y, z;

    // Instantiate design test code
    question4 uut (
        .a(p),
        .b(q),
        .c(r),
        .d(s),
        .w(w),
        .x(x),
        .y(y),
        .z(z)
    );

    // VCD Dump setup
    initial begin
        $dumpfile("dump.vcd");
        $dumpvars(1);
    end

    // Monitor output to console
    initial begin
        $monitor("Time=%0t | Inputs: p=%b q=%b r=%b s=%b | Outputs: w=%b x=%b y=%b z=%b",
                 $time, p, q, r, s, w, x, y, z);
    end

    // Stimulus generation (all 10 valid BCD inputs)
    initial begin
        p = 0; q = 0; r = 0; s = 0; #5;
        p = 0; q = 0; r = 0; s = 1; #5;
        p = 0; q = 0; r = 1; s = 0; #5;
        p = 0; q = 0; r = 1; s = 1; #5;
        p = 0; q = 1; r = 0; s = 0; #5;
        p = 0; q = 1; r = 0; s = 1; #5;
        p = 0; q = 1; r = 1; s = 0; #5;
        p = 0; q = 1; r = 1; s = 1; #5;
        p = 1; q = 0; r = 0; s = 0; #5;
        p = 1; q = 0; r = 0; s = 1; #5;
        $finish;
    end

endmodule

veri/assign4/Q4_bcd2ex3/dump.vcd
$date
	Tue Sep 22 14:45:34 2026
$end
$version
	Icarus Verilog
$end
$timescale
	1s
$end
$scope module tb_question4 $end
$var wire 1 ! z $end
$var wire 1 " y $end
$var wire 1 # x $end
$var wire 1 $ w $end
$var reg 1 % p $end
$var reg 1 & q $end
$var reg 1 ' r $end
$var reg 1 ( s $end
$upscope $end
$enddefinitions $end
$comment Show the parameter values. $end
$dumpall
$end
#0
$dumpvars
0(
0'
0&
0%
0$
0#
1"
1!
$end
#5
1#
0"
0!
1(
#10
1!
0(
1'
#15
1"
0!
1(
#20
1!
0(
0'
1&
#25
0#
0"
1$
0!
1(
#30
1!
0(
1'
#35
1"
0!
1(
#40
1!
0(
0'
0&
1%
#45
1#
0"
0!
1(
